Metadata-Version: 1.1
Name: ameba
Version: 1.0
Summary: AMEBA: Advanced MEtabolic Branchpoint Analysis
Home-page: http://metano.tu-bs.de/ameba
Author: Rene Rex, Alexander Riemer and Julia Helmecke
Author-email: j.helmecke@tu-bs.de
License: GPL
Keywords: genome-scale metabolic models flux balance analysis
Platform: UNKNOWN
Classifier: License :: OSI Approved :: GNU General Public License (GPL)
Classifier: Programming Language :: Python
Classifier: Development Status :: 5 - Production/Stable
Classifier: Intended Audience :: Science/Research
Classifier: Topic :: Scientific/Engineering :: Bio-Informatics
Classifier: Topic :: Scientific/Engineering :: Visualization
